colorblast/__init__.py
colorblast/core.py
colorblast-1.0.1.dist-info/METADATA
colorblast-1.0.1.dist-info/WHEEL
colorblast-1.0.1.dist-info/top_level.txt
colorblast-1.0.1.dist-info/RECORD
