Metadata-Version: 2.4
Name: colorblast
Version: 1.0.1
Summary: The ultimate colorful and animated print library for Python
Author-email: Liam <lukaeisen7@gmail.com>
License: MIT
Keywords: print,console,color,animation,terminal,logging
Classifier: Programming Language :: Python :: 3
Classifier: License :: OSI Approved :: MIT License
Classifier: Operating System :: OS Independent
Classifier: Intended Audience :: Developers
Classifier: Topic :: Software Development :: Libraries
Classifier: Topic :: Utilities
Requires-Python: >=3.6
